MANIFEST.in
README.rst
setup.cfg
setup.py
django_socialprofile.egg-info/PKG-INFO
django_socialprofile.egg-info/SOURCES.txt
django_socialprofile.egg-info/dependency_links.txt
django_socialprofile.egg-info/requires.txt
django_socialprofile.egg-info/top_level.txt
django_socialprofile.egg-info/zip-safe
socialprofile/__init__.py
socialprofile/admin.py
socialprofile/apps.py
socialprofile/forms.py
socialprofile/models.py
socialprofile/pipeline.py
socialprofile/tests.py
socialprofile/tests_forms.py
socialprofile/tests_pipeline.py
socialprofile/urls.py
socialprofile/views.py
socialprofile/templates/socialprofile/sp_account_select.html
socialprofile/templates/socialprofile/sp_delete_account_modal.html
socialprofile/templates/socialprofile/sp_profile_edit.html
socialprofile/templates/socialprofile/sp_profile_view.html
socialprofile/templatetags/__init__.py
socialprofile/templatetags/socialprofile_tags.py