Metadata-Version: 1.1
Name: django-socialprofile
Version: 1.2.1
Summary: django-socialprofile enables users to manage their user profile built by logging in via a social     service such as Google, Twitter, or Facebook. It relies on python-socialauth.
Home-page: https://github.com/cyface/django-socialprofile
Author: Tim White
Author-email: tim@cyface.com
License: BSD
Platform: UNKNOWN
Classifier: Development Status :: 5 - Production/Stable
Classifier: Framework :: Django
Classifier: Intended Audience :: Developers
Classifier: License :: OSI Approved :: BSD License
Classifier: Operating System :: OS Independent
Classifier: Programming Language :: Python :: 2
Classifier: Programming Language :: Python :: 2.7
Classifier: Programming Language :: Python :: 3
Classifier: Programming Language :: Python :: 3.5
Classifier: Topic :: Internet :: WWW/HTTP
